nonebot_plugin_getbapics/Debug/show_database.py
nonebot_plugin_getbapics/__init__.py
nonebot_plugin_getbapics/config.py
nonebot_plugin_getbapics/utils.py
nonebot_plugin_getbapics-0.1.5.dist-info/LICENSE
nonebot_plugin_getbapics-0.1.5.dist-info/METADATA
nonebot_plugin_getbapics-0.1.5.dist-info/WHEEL
nonebot_plugin_getbapics-0.1.5.dist-info/RECORD
