Metadata-Version: 2.1
Name: nonebot_plugin_getbapics
Version: 0.1.5
Summary: Get BlueArchive Pictures
Home-page: https://github.com/hanasa2023/nonebot-plugin-getbapics
License: MIT
Author: hanasa2023
Author-email: hanasakayui2022@gmail.com
Requires-Python: >=3.10,<4.0
Classifier: License :: OSI Approved :: MIT License
Classifier: Programming Language :: Python :: 3
Classifier: Programming Language :: Python :: 3.10
Classifier: Programming Language :: Python :: 3.11
Requires-Dist: aiofiles (>=23.2.1,<24.0.0)
Requires-Dist: aiohttp (>=3.8.6,<4.0.0)
Requires-Dist: nonebot-adapter-red (>=0.6.0,<0.7.0)
Requires-Dist: nonebot2 (>=2.1.1,<3.0.0)
Project-URL: Documentation, https://github.com/hanasa2023/nonebot-plugin-getbapics/blob/master/README.md
